automol/__init__.py
autoreact/__init__.py
molsym/__init__.py
phydat/__init__.py
test_autochem-0.3.0.dist-info/METADATA
test_autochem-0.3.0.dist-info/WHEEL
test_autochem-0.3.0.dist-info/RECORD
